hexnumgen-0.4.0.dist-info/METADATA
hexnumgen-0.4.0.dist-info/WHEEL
hexnumgen-0.4.0.dist-info/licenses/LICENSE
hexnumgen/__init__.py
hexnumgen/__init__.pyi
hexnumgen/hexnumgen.cpython-312-s390x-linux-gnu.so
hexnumgen/py.typed
hexnumgen-0.4.0.dist-info/RECORD
