Metadata-Version: 2.4
Name: hexnumgen
Version: 0.4.0
License-File: LICENSE
Summary: Number literal generator for the Hex Casting mod for Minecraft.
Keywords: hexcasting
Author: object-Object
License-Expression: MIT
Requires-Python: >=3.11
Project-URL: Repository, https://github.com/object-Object/hexnumgen-rs
Project-URL: Issues, https://github.com/object-Object/hexnumgen-rs/issues
Project-URL: Changelog, https://github.com/object-Object/hexnumgen-rs/blob/main/CHANGELOG.md
